gflick/__init__.py
gflick/db.py
gflick/google.py
gflick/server.py
gflick-0.1.9.dist-info/entry_points.txt
gflick-0.1.9.dist-info/WHEEL
gflick-0.1.9.dist-info/METADATA
gflick-0.1.9.dist-info/RECORD
